README.txt
buildout.cfg
setup.py
src/zc/__init__.py
src/zc.s3uploadqueue.egg-info/PKG-INFO
src/zc.s3uploadqueue.egg-info/SOURCES.txt
src/zc.s3uploadqueue.egg-info/dependency_links.txt
src/zc.s3uploadqueue.egg-info/entry_points.txt
src/zc.s3uploadqueue.egg-info/namespace_packages.txt
src/zc.s3uploadqueue.egg-info/not-zip-safe
src/zc.s3uploadqueue.egg-info/requires.txt
src/zc.s3uploadqueue.egg-info/top_level.txt
src/zc/s3uploadqueue/README.txt
src/zc/s3uploadqueue/__init__.py
src/zc/s3uploadqueue/tests.py