Metadata-Version: 1.0
Name: zc.s3uploadqueue
Version: 0.1.1
Summary: zc.s3uploadqueue
Home-page: UNKNOWN
Author: Jim Fulton
Author-email: jim@zope.com
License: ZPL 2.1
Platform: UNKNOWN
